CHANGELOG.md
LICENSE
TODO.md
netgate_xml_to_xlsx/__init__.py
netgate_xml_to_xlsx/errors.py
netgate_xml_to_xlsx/main.py
netgate_xml_to_xlsx/mytypes.py
netgate_xml_to_xlsx/parse_args.py
netgate_xml_to_xlsx/pfsense.py
netgate_xml_to_xlsx/plugin_tools.py
netgate_xml_to_xlsx/plugins/__init__.py
netgate_xml_to_xlsx/plugins/base_plugin.py
netgate_xml_to_xlsx/plugins/plugin_aliases/__init__.py
netgate_xml_to_xlsx/plugins/plugin_aliases/aliases.py
netgate_xml_to_xlsx/plugins/plugin_ca/__init__.py
netgate_xml_to_xlsx/plugins/plugin_ca/ca.py
netgate_xml_to_xlsx/plugins/plugin_cert/__init__.py
netgate_xml_to_xlsx/plugins/plugin_cert/cert.py
netgate_xml_to_xlsx/plugins/plugin_cron/__init__.py
netgate_xml_to_xlsx/plugins/plugin_cron/cron.py
netgate_xml_to_xlsx/plugins/plugin_dhcpd/__init__.py
netgate_xml_to_xlsx/plugins/plugin_dhcpd/dhcpd.py
netgate_xml_to_xlsx/plugins/plugin_dhcpdv6/__init__.py
netgate_xml_to_xlsx/plugins/plugin_dhcpdv6/dhcpdv6.py
netgate_xml_to_xlsx/plugins/plugin_diag/__init__.py
netgate_xml_to_xlsx/plugins/plugin_diag/diag.py
netgate_xml_to_xlsx/plugins/plugin_dnshaper/__init__.py
netgate_xml_to_xlsx/plugins/plugin_dnshaper/dnshaper.py
netgate_xml_to_xlsx/plugins/plugin_filter/__init__.py
netgate_xml_to_xlsx/plugins/plugin_filter/filter.py
netgate_xml_to_xlsx/plugins/plugin_gateways/__init__.py
netgate_xml_to_xlsx/plugins/plugin_gateways/gateways.py
netgate_xml_to_xlsx/plugins/plugin_haproxy/__init__.py
netgate_xml_to_xlsx/plugins/plugin_haproxy/haproxy.py
netgate_xml_to_xlsx/plugins/plugin_hasync/__init__.py
netgate_xml_to_xlsx/plugins/plugin_hasync/hasync.py
netgate_xml_to_xlsx/plugins/plugin_ifgroups/__init__.py
netgate_xml_to_xlsx/plugins/plugin_ifgroups/ifgroups.py
netgate_xml_to_xlsx/plugins/plugin_installedpackages/__init__.py
netgate_xml_to_xlsx/plugins/plugin_installedpackages/installed_packages.py
netgate_xml_to_xlsx/plugins/plugin_interfaces/__init__.py
netgate_xml_to_xlsx/plugins/plugin_interfaces/interfaces.py
netgate_xml_to_xlsx-0.9.8.dist-info/entry_points.txt
netgate_xml_to_xlsx-0.9.8.dist-info/LICENSE
netgate_xml_to_xlsx-0.9.8.dist-info/WHEEL
netgate_xml_to_xlsx-0.9.8.dist-info/METADATA
netgate_xml_to_xlsx-0.9.8.dist-info/RECORD
