Metadata-Version: 2.1
Name: netgate-xml-to-xlsx
Version: 0.9.8
Summary: Translate Netgate firewall rules to spreadsheet for review.
Home-page: https://gitlab.com/appropriate-solutions-inc/netgate-xml-to-xlsx
License: BSD-3-Clause
Keywords: firewall,netgate
Author: Raymond GA Côté
Author-email: ray@AppropriateSolutions.com
Requires-Python: >=3.10,<4.0
Classifier: Development Status :: 3 - Alpha
Classifier: Intended Audience :: Developers
Classifier: Intended Audience :: Information Technology
Classifier: Intended Audience :: System Administrators
Classifier: License :: OSI Approved :: BSD License
Classifier: Natural Language :: English
Classifier: Operating System :: OS Independent
Classifier: Programming Language :: Python
Classifier: Programming Language :: Python :: 3
Classifier: Programming Language :: Python :: 3 :: Only
Classifier: Programming Language :: Python :: 3.10
Classifier: Topic :: System :: Networking :: Firewalls
Classifier: Topic :: Utilities
Requires-Dist: defusedxml (>=0.7.1,<0.8.0)
Requires-Dist: lxml (>=4.8.0,<5.0.0)
Requires-Dist: openpyxl (>=3.0.9,<4.0.0)
Requires-Dist: toml (>=0.10.2,<0.11.0)
Requires-Dist: xmltodict (>=0.13.0,<0.14.0)
Project-URL: Repository, https://gitlab.com/appropriate-solutions-inc/netgate-xml-to-xlsx.git
